seqerakit/__init__.py
seqerakit/cli.py
seqerakit/computeenvs.py
seqerakit/helper.py
seqerakit/on_exists.py
seqerakit/overwrite.py
seqerakit/pipelines.py
seqerakit/seqeraplatform.py
seqerakit/utils.py
seqerakit-0.5.6.dist-info/licenses/LICENSE.txt
seqerakit-0.5.6.dist-info/METADATA
seqerakit-0.5.6.dist-info/WHEEL
seqerakit-0.5.6.dist-info/entry_points.txt
seqerakit-0.5.6.dist-info/top_level.txt
seqerakit-0.5.6.dist-info/RECORD
