Metadata-Version: 2.4
Name: seqerakit
Version: 0.5.6
Summary: Automate creation of Seqera Platform resources
Author-email: Esha Joshi <esha.joshi@seqera.io>, Adam Talbot <adam.talbot@seqera.io>, Harshil Patel <harshil.patel@seqera.io>
Maintainer-email: Esha Joshi <esha.joshi@seqera.io>
Project-URL: Homepage, https://seqera.io/
Project-URL: Documentation, https://docs.seqera.io/platform/24.2/seqerakit/installation
Project-URL: Repository, https://github.com/seqeralabs/seqera-kit
Project-URL: Issues, https://github.com/seqeralabs/seqera-kit/issues
Project-URL: Changelog, https://github.com/seqeralabs/seqera-kit/releases
Keywords: nextflow,bioinformatics,workflow,pipeline,seqera-platform,seqera
Classifier: License :: OSI Approved :: Apache Software License
Requires-Python: <4,>=3.8
License-File: LICENSE.txt
Requires-Dist: pyyaml>=6.0.0
Dynamic: license-file
